praisonaippt/__init__.py
praisonaippt/cli.py
praisonaippt/config.py
praisonaippt/core.py
praisonaippt/gdrive_uploader.py
praisonaippt/lazy_loader.py
praisonaippt/loader.py
praisonaippt/pdf_converter.py
praisonaippt/utils.py
praisonaippt-1.4.0.dist-info/licenses/LICENSE
praisonaippt-1.4.0.dist-info/METADATA
praisonaippt-1.4.0.dist-info/WHEEL
praisonaippt-1.4.0.dist-info/entry_points.txt
praisonaippt-1.4.0.dist-info/top_level.txt
praisonaippt-1.4.0.dist-info/RECORD
