Metadata-Version: 2.4
Name: praisonaippt
Version: 1.4.0
Summary: PraisonAI PPT - Create beautiful PowerPoint presentations from Bible verses in JSON format
Home-page: https://github.com/MervinPraison/PraisonAIPPT
Author: MervinPraison
License-Expression: MIT
Project-URL: Homepage, https://github.com/MervinPraison/PraisonAIPPT
Project-URL: Bug Reports, https://github.com/MervinPraison/PraisonAIPPT/issues
Project-URL: Source, https://github.com/MervinPraison/PraisonAIPPT
Keywords: powerpoint,pptx,bible,verses,presentation,generator,praisonai
Classifier: Development Status :: 4 - Beta
Classifier: Intended Audience :: End Users/Desktop
Classifier: Topic :: Religion
Classifier: Topic :: Office/Business :: Office Suites
Classifier: Programming Language :: Python :: 3
Classifier: Programming Language :: Python :: 3.7
Classifier: Programming Language :: Python :: 3.8
Classifier: Programming Language :: Python :: 3.9
Classifier: Programming Language :: Python :: 3.10
Classifier: Programming Language :: Python :: 3.11
Classifier: Programming Language :: Python :: 3.12
Requires-Python: >=3.7
License-File: LICENSE
Requires-Dist: python-pptx>=0.6.21
Requires-Dist: PyYAML>=6.0
Dynamic: home-page
Dynamic: license-file
Dynamic: requires-python
